Py2048_Engine/Exceptions.py
Py2048_Engine/Game.py
Py2048_Engine/Test.py
Py2048_Engine-1.0.0.dist-info/LICENSE
Py2048_Engine-1.0.0.dist-info/METADATA
Py2048_Engine-1.0.0.dist-info/WHEEL
Py2048_Engine-1.0.0.dist-info/top_level.txt
Py2048_Engine-1.0.0.dist-info/RECORD
