Metadata-Version: 2.1
Name: Py2048-Engine
Version: 1.0.0
Summary: A pure Python 2048 engine, based on the original game!
Home-page: https://github.com/http-samc/2048.py
Author: Samarth Chitgopekar
Author-email: sam@chitgopekar.tech
License: UNKNOWN
Platform: UNKNOWN
Classifier: Topic :: Utilities
Classifier: Intended Audience :: Developers
Classifier: Development Status :: 5 - Production/Stable
Classifier: License :: OSI Approved :: MIT License
Classifier: Operating System :: OS Independent
Classifier: Programming Language :: Python :: 3.9
Classifier: Natural Language :: English
